optimodel_guard/__init__.py
optimodel_guard/cli.py
optimodel_guard/index.py
optimodel_guard/Guards/GuardBaseClass.py
optimodel_guard/Guards/LLamaPromptGuard.py
optimodel_guard/Guards/MicrosoftPresidioGuard.py
optimodel_guard/Guards/RegexGuard.py
optimodel_guard/Guards/__init__.py
optimodel_guard_server-0.4.1.dist-info/METADATA
optimodel_guard_server-0.4.1.dist-info/WHEEL
optimodel_guard_server-0.4.1.dist-info/entry_points.txt
optimodel_guard_server-0.4.1.dist-info/top_level.txt
optimodel_guard_server-0.4.1.dist-info/RECORD
