Metadata-Version: 2.1
Name: optimodel-guard-server
Version: 0.4.1
Summary: A smart framework for calling models in the most efficient way possible
Author-email: Lytix <support@lytix.com>
Project-URL: Homepage, https://github.com/Lytix-Labs/optimodel
Project-URL: Issues, https://github.com/Lytix-Labs/optimodel/issues
Classifier: Programming Language :: Python :: 3
Classifier: License :: OSI Approved :: MIT License
Classifier: Operating System :: OS Independent
Requires-Python: >=3.8
Requires-Dist: requests ==2.31.0
Requires-Dist: urllib3 ==2.2.1
Requires-Dist: fastapi ==0.111.0
Requires-Dist: transformers ==4.43.3
Requires-Dist: torch ==2.4.0
Requires-Dist: torchvision ==0.19.0
Requires-Dist: accelerate ==0.33.0
Requires-Dist: optimodel-server ==1.8.21
Requires-Dist: presidio-analyzer[transformers] ==2.2.355
Requires-Dist: presidio-anonymizer ==2.2.355
Requires-Dist: optimodel-types ==0.0.3
